frequenz/gridpool/__init__.py
frequenz/gridpool/_graph_generator.py
frequenz/gridpool/_microgrid_config.py
frequenz/gridpool/conftest.py
frequenz/gridpool/py.typed
frequenz/gridpool/cli/__init__.py
frequenz/gridpool/cli/__main__.py
frequenz_gridpool-0.3.0.dist-info/licenses/LICENSE
frequenz_gridpool-0.3.0.dist-info/METADATA
frequenz_gridpool-0.3.0.dist-info/WHEEL
frequenz_gridpool-0.3.0.dist-info/entry_points.txt
frequenz_gridpool-0.3.0.dist-info/top_level.txt
frequenz_gridpool-0.3.0.dist-info/RECORD
