Metadata-Version: 2.4
Name: frequenz-gridpool
Version: 0.3.0
Summary: High-level interface to grid pools for the Frequenz platform.
Author-email: Frequenz Energy-as-a-Service GmbH <floss@frequenz.com>
License: MIT
Project-URL: Documentation, https://frequenz-floss.github.io/frequenz-gridpool-python/
Project-URL: Changelog, https://github.com/frequenz-floss/frequenz-gridpool-python/releases
Project-URL: Issues, https://github.com/frequenz-floss/frequenz-gridpool-python/issues
Project-URL: Repository, https://github.com/frequenz-floss/frequenz-gridpool-python
Project-URL: Support, https://github.com/frequenz-floss/frequenz-gridpool-python/discussions/categories/support
Keywords: frequenz,python,lib,library,gridpool
Classifier: Development Status :: 3 - Alpha
Classifier: Intended Audience :: Developers
Classifier: License :: OSI Approved :: MIT License
Classifier: Programming Language :: Python :: 3
Classifier: Programming Language :: Python :: 3 :: Only
Classifier: Topic :: Software Development :: Libraries
Classifier: Typing :: Typed
Requires-Python: <4,>=3.11
License-File: LICENSE
Requires-Dist: marshmallow-dataclass<9,>=8.7.1
Requires-Dist: asyncclick<9,>=8.3.0.4
Requires-Dist: typing-extensions<5,>=4.14.1
Requires-Dist: frequenz-microgrid-component-graph<0.4,>=0.3.4
Requires-Dist: frequenz-client-assets<0.3,>=0.2.0
Provides-Extra: dev-flake8
Requires-Dist: flake8==7.3.0; extra == "dev-flake8"
Requires-Dist: flake8-docstrings==1.7.0; extra == "dev-flake8"
Requires-Dist: flake8-pyproject==1.2.4; extra == "dev-flake8"
Requires-Dist: pydoclint==0.8.3; extra == "dev-flake8"
Requires-Dist: pydocstyle==6.3.0; extra == "dev-flake8"
Provides-Extra: dev-formatting
Requires-Dist: black==25.11.0; extra == "dev-formatting"
Requires-Dist: isort==7.0.0; extra == "dev-formatting"
Provides-Extra: dev-mkdocs
Requires-Dist: Markdown==3.10; extra == "dev-mkdocs"
Requires-Dist: black==25.11.0; extra == "dev-mkdocs"
Requires-Dist: mike==2.1.3; extra == "dev-mkdocs"
Requires-Dist: mkdocs-gen-files==0.5.0; extra == "dev-mkdocs"
Requires-Dist: mkdocs-literate-nav==0.6.2; extra == "dev-mkdocs"
Requires-Dist: mkdocs-macros-plugin==1.5.0; extra == "dev-mkdocs"
Requires-Dist: mkdocs-material==9.7.0; extra == "dev-mkdocs"
Requires-Dist: mkdocstrings[python]==1.0.0; extra == "dev-mkdocs"
Requires-Dist: mkdocstrings-python==1.19.0; extra == "dev-mkdocs"
Requires-Dist: frequenz-repo-config[lib]==0.13.7; extra == "dev-mkdocs"
Provides-Extra: dev-mypy
Requires-Dist: mypy==1.19.0; extra == "dev-mypy"
Requires-Dist: types-Markdown==3.10.0.20251106; extra == "dev-mypy"
Requires-Dist: frequenz-gridpool[dev-mkdocs,dev-noxfile,dev-pytest]; extra == "dev-mypy"
Provides-Extra: dev-noxfile
Requires-Dist: nox==2025.11.12; extra == "dev-noxfile"
Requires-Dist: frequenz-repo-config[lib]==0.13.7; extra == "dev-noxfile"
Provides-Extra: dev-pylint
Requires-Dist: frequenz-gridpool[dev-mkdocs,dev-noxfile,dev-pytest]; extra == "dev-pylint"
Provides-Extra: dev-pytest
Requires-Dist: pytest==8.4.1; extra == "dev-pytest"
Requires-Dist: pylint==4.0.4; extra == "dev-pytest"
Requires-Dist: frequenz-repo-config[extra-lint-examples]==0.13.7; extra == "dev-pytest"
Requires-Dist: pytest-mock==3.15.1; extra == "dev-pytest"
Requires-Dist: pytest-asyncio==1.3.0; extra == "dev-pytest"
Requires-Dist: async-solipsism==0.9; extra == "dev-pytest"
Provides-Extra: dev
Requires-Dist: frequenz-gridpool[dev-flake8,dev-formatting,dev-mkdocs,dev-mypy,dev-noxfile,dev-pylint,dev-pytest]; extra == "dev"
Dynamic: license-file
